{ "signal": [ "", { "name": "Running", "wave": "4..zzzz2...3..2.4zzz54..zz2zz3zz43...4.zzz3.35.25.33335...5.33333333.42443..2442...5555335..3333332.35525552...25.2.222222.553332.22.3333335..52.222.222..555552..2222222235552..222..5555555552..5555555555552555.333333444444443525..53333..5.344543...443.444333.445...354544444333..444444445.4333344445.3444444445...3333..444444.44444443...44444444z4444444zz4.z4..z4zzz4..z4.zzzzz4zzzzzz4...zz4...zzzz4z", "data": [ "A", "B", "D", "B", "C", "E", "C", "B", "D", "C", "F", "C", "G", "F", "H", "B", "H", "G", "D", "F", "G", "H", "I", "F", "G", "D", "F", "D", "G", "D", "G", "J", "B", "K", "J", "F", "L", "C", "J", "B", "H", "I", "H", "I", "D", "G", "I", "D", "F", "N", "G", "D", "N", "L", "F", "I", "H", "O", "I", "H", "I", "L", "B", "I", "Q", "R", "O", "Q", "O", "Q", "O", "H", "I", "F", "N", "G", "O", "L", "O", "F", "T", "N", "G", "T", "N", "V", "H", "Q", "O", "Q", "O", "L", "O", "L", "H", "I", "H", "I", "V", "X", "L", "X", "L", "O", "L", "X", "L", "X", "F", "Y", "H", "Y", "Q", "L", "Q", "L", "H", "V", "Y", "Z", "I", "H", "V", "Y", "I", "O", "V", "H", "Z", "H", "I", "V", "Z", "V", "I", "Y", "I", "V", "O", "Z", "V", "Z", "T", "G", "N", "T", "F", "G", "M", "J", "K", "P", "S", "U", "W", "C", "T", "Y", "O", "Z", "V", "G", "N", "G", "F", "Z", "F", "M", "J", "V", "P", "T", "S", "U", "N", "W", "C", "M", "T", "F", "T", "K", "P", "Z", "N", "V", "S", "Z", "W", "J", "C", "K", "P", "T", "N", "T", "W", "M", "U", "K", "C", "P", "J", "M", "Z", "W", "T", "N", "T", "N", "C", "P", "J", "U", "Z", "T", "J", "P", "C", "M", "P", "U", "C", "P", "Z", "N", "T", "N", "T", "U", "P", "J", "M", "J", "P", "U", "P", "U", "J", "U", "J", "U", "T", "P", "M", "P", "U", "P", "J", "P", "J", "U", "M", "U", "M", "U", "M", "U", "P", "J", "M", "U", "U", "M", "U", "M", "M" ] }, { "name": "A", "wave": "4..u.............................................................................................................................................................................................................................................................................................................................................................................................................", "data": [ "A" ] }, { "name": "B", "wave": "d......2...x..2.x.........2x...................2x.....................2x.......2...x...........................2u................................................................................................................................................................................................................................................................................................", "data": [ "B", "B", "B", "B", "B", "B", "B" ] }, { "name": "C", "wave": "d.........z.....4x...4..x.......4z...4.x.....z...............................4z.................................................................................................................................................4z............................4z................4x..........4z.........4x......z4z..4u...........................................................................................", "data": [ "C", "C", "C", "C", "C", "C", "C", "C", "C", "C", "C", "C" ] }, { "name": "D", "wave": "d.........z3..x..............3x................z...3z.........3z3z3x..................z3z...3z..3u...............................................................................................................................................................................................................................................................................................................", "data": [ "D", "D", "D", "D", "D", "D", "D", "D", "D" ] }, { "name": "E", "wave": "d...................5u...........................................................................................................................................................................................................................................................................................................................................................................................", "data": [ "E" ] }, { "name": "F", "wave": "d................................3...x......3z......3z......3z.3x........3..x..............z.3z.....3x........z..............3z......3z...................................3z...........................................3x.........z........3..z.3x..............z3u..............................................................................................................................................", "data": [ "F", "F", "F", "F", "F", "F", "F", "F", "F", "F", "F", "F", "F", "F", "F" ] }, { "name": "G", "wave": "d.........................................3.z.....3z.3x..z...3z..3z3.x..............z...3z.....3z..............................3z.......3x........z.................................................................3z..3x.............z3z3u.....................................................................................................................................................................", "data": [ "G", "G", "G", "G", "G", "G", "G", "G", "G", "G", "G", "G", "G", "G" ] }, { "name": "H", "wave": "d............................................5.z5.x...5...x......................z.5z5x...............5z.5x.......z........5x.................5x..........5z5x.............z5z........5xz..5z......5z5u..........................................................................................................................................................................................................", "data": [ "H", "H", "H", "H", "H", "H", "H", "H", "H", "H", "H", "H", "H", "H", "H", "H" ] }, { "name": "I", "wave": "d.........................................................5.x.......................5z5x.5..x........5z.5z5x..z.5.z.........5x....................z........5z5x...............z...........5z..5x......5x..5z5u...................................................................................................................................................................................................", "data": [ "I", "I", "I", "I", "I", "I", "I", "I", "I", "I", "I", "I", "I", "I", "I", "I" ] }, { "name": "J", "wave": "d.........................................................z..........4z.4z....4x..z.......................................................................................................................................4z......................4x...........z...............4z.............4z.........4z...4x....z.............4z4x..z.4z4z.........4z4x............4..u......................................", "data": [ "J", "J", "J", "J", "J", "J", "J", "J", "J", "J", "J", "J", "J", "J", "J", "J" ] }, { "name": "K", "wave": "d...................................................................z..4x.............z....................................................................................................................................4z.......................................4z...........4z........4u....................................................................................................................", "data": [ "K", "K", "K", "K", "K" ] }, { "name": "L", "wave": "d...........................................................................2x....................2.x......2...x..................2x.................2z2..x.......2z2z2z2x.......2z2..u..........................................................................................................................................................................................................................", "data": [ "L", "L", "L", "L", "L", "L", "L", "L", "L", "L", "L", "L" ] }, { "name": "M", "wave": "d................................................................................z.......................................................................................................................................4z......................4z............4z........................4x..z.4x............z...4z................4x...........z..4x.......4z4z4x.........4x.............4x...........4...x...4u", "data": [ "M", "M", "M", "M", "M", "M", "M", "M", "M", "M", "M", "M", "M", "M", "M" ] }, { "name": "N", "wave": "d...........................................................................................z.3z.3x................z..........3z.......3z.3z.........................................................................3x.................z3x................3.x...........z3x........3x..............3z3x...............z..3z3u...................................................................................", "data": [ "N", "N", "N", "N", "N", "N", "N", "N", "N", "N", "N", "N", "N", "N" ] }, { "name": "O", "wave": "d......................................................................................................2x............2z2z2.x....2.z2.x...........2z2.z2x...........z.2x........................2..x...........2x...................2u............................................................................................................................................................................", "data": [ "O", "O", "O", "O", "O", "O", "O", "O", "O", "O", "O", "O", "O" ] }, { "name": "P", "wave": "d.............................................................................................................z.............................................................................................................4z......................4z...............4z...........4x........z4x........z4z.....4z.4z.4x..z.......4z..4.z4x.....z..4z4z4z4x..........4.u..........................................", "data": [ "P", "P", "P", "P", "P", "P", "P", "P", "P", "P", "P", "P", "P", "P", "P", "P", "P" ] }, { "name": "Q", "wave": "d.................................................................................................................2.z.2z2x.....................2.z2x..........................2..z2u.............................................................................................................................................................................................................................", "data": [ "Q", "Q", "Q", "Q", "Q", "Q", "Q" ] }, { "name": "R", "wave": "d...................................................................................................................2u...........................................................................................................................................................................................................................................................................................", "data": [ "R" ] }, { "name": "S", "wave": "d......................................................................................................................z.....................................................................................................4z..........................4z.................4u...................................................................................................................................", "data": [ "S", "S", "S" ] }, { "name": "T", "wave": "d..............................................................................................................................z......3z.3z........................................................................3z.3x.........3x..................3...x......3z3.x..............3z3..x..........3z3x....z.3x.......z....3z3..x.............3...u..............................................................", "data": [ "T", "T", "T", "T", "T", "T", "T", "T", "T", "T", "T", "T", "T", "T", "T", "T" ] }, { "name": "U", "wave": "d...................................................................................................................................z.........................................................................................4z..........................4z..............................4x........z.....4x.....z.4z...........4x.....4z4z4z4x.....z4x....4z4z4z4x............4..x4.x...........4...u...........", "data": [ "U", "U", "U", "U", "U", "U", "U", "U", "U", "U", "U", "U", "U", "U", "U", "U", "U", "U" ] }, { "name": "V", "wave": "d..........................................................................................................................................5..x.............z.5x......................z5z...5z....5x...5z5z..5z.5x.....................5x..........5x......................5u....................................................................................................................................", "data": [ "V", "V", "V", "V", "V", "V", "V", "V", "V", "V", "V", "V" ] }, { "name": "W", "wave": "d.......................................................................................................................................................z......................................................................4z............................4z...............4z........4x..z.....4u.............................................................................................................", "data": [ "W", "W", "W", "W", "W" ] }, { "name": "X", "wave": "d..............................................................................................................................................................2..z2xz.2z2u......................................................................................................................................................................................................................................", "data": [ "X", "X", "X", "X" ] }, { "name": "Y", "wave": "d..........................................................................................................................................................................5z5z.........5z...5x...........z5x.....................5u.............................................................................................................................................................................", "data": [ "Y", "Y", "Y", "Y", "Y", "Y" ] }, { "name": "Z", "wave": "d......................................................................................................................................................................................z.5z.........5z..5x.....5z5.x................5..x......5.x.....................5...x..5x.................5.x........5.x........5...u......................................................................................", "data": [ "Z", "Z", "Z", "Z", "Z", "Z", "Z", "Z", "Z", "Z", "Z", "Z" ] }, [ "Legend", { "name": "Running", "wave": "2.....", "data": [ "Priority 0" ] }, { "name": "Running", "wave": "5.....", "data": [ "Priority 1" ] }, { "name": "Running", "wave": "3.....", "data": [ "Priority 2" ] }, { "name": "Running", "wave": "4.....", "data": [ "Priority 3" ] }, { "name": "Blocked", "wave": "x.....", "data": [] }, { "name": "Ready", "wave": "z.....", "data": [] }, { "name": "Not Arrived", "wave": "d.....", "data": [] }, { "name": "Finished", "wave": "u.....", "data": [] } ] ] }